airflow_balancer/__init__.py
airflow_balancer/testing.py
airflow_balancer/config/__init__.py
airflow_balancer/tests/test_config.py
airflow_balancer/tests/test_host.py
airflow_balancer/tests/test_port.py
airflow_balancer/tests/test_ui.py
airflow_balancer/tests/config/config.yaml
airflow_balancer/tests/config/extensions/balancer.yaml
airflow_balancer/tests/config/extensions/default.yaml
airflow_balancer/tests/config/extensions/second.yaml
airflow_balancer/ui/__init__.py
airflow_balancer/ui/airflow.py
airflow_balancer/ui/functions.py
airflow_balancer/ui/standalone/__init__.py
airflow_balancer/ui/standalone/__main__.py
airflow_balancer/ui/standalone/static/airflowDefaultTheme.css
airflow_balancer/ui/standalone/static/main.css
airflow_balancer/ui/standalone/static/materialIcons.css
airflow_balancer/ui/standalone/templates/airflow_mock.html
airflow_balancer/ui/static/cdn/index.js
airflow_balancer/ui/static/cdn/index.js.map
airflow_balancer/ui/static/css/index.css
airflow_balancer/ui/templates/airflow_balancer/404.html
airflow_balancer/ui/templates/airflow_balancer/500.html
airflow_balancer/ui/templates/airflow_balancer/home.html
airflow_balancer/ui/templates/airflow_balancer/hosts.html
airflow_balancer-0.7.7.dist-info/METADATA
airflow_balancer-0.7.7.dist-info/WHEEL
airflow_balancer-0.7.7.dist-info/entry_points.txt
airflow_balancer-0.7.7.dist-info/licenses/LICENSE
airflow_balancer-0.7.7.dist-info/RECORD
