Metadata-Version: 2.4
Name: airflow-balancer
Version: 0.7.7
Summary: Utilities for tracking hosts and ports and load balancing DAGs
Project-URL: Repository, https://github.com/airflow-laminar/airflow-balancer
Project-URL: Homepage, https://github.com/airflow-laminar/airflow-balancer
Author-email: the airflow-balancer authors <t.paine154@gmail.com>
License: Apache-2.0
License-File: LICENSE
Classifier: Development Status :: 3 - Alpha
Classifier: Programming Language :: Python
Classifier: Programming Language :: Python :: 3
Classifier: Programming Language :: Python :: 3.9
Classifier: Programming Language :: Python :: 3.10
Classifier: Programming Language :: Python :: 3.11
Classifier: Programming Language :: Python :: 3.12
Classifier: Programming Language :: Python :: 3.13
Classifier: Programming Language :: Python :: 3.14
Classifier: Programming Language :: Python :: Implementation :: CPython
Classifier: Programming Language :: Python :: Implementation :: PyPy
Requires-Python: >=3.9
Requires-Dist: airflow-config<1.12,>=1.10
Requires-Dist: airflow-pydantic<1.6,>=1.4
Requires-Dist: paramiko<4
Requires-Dist: pydantic>=2
Provides-Extra: develop
Requires-Dist: apache-airflow-providers-ssh; extra == 'develop'
Requires-Dist: apache-airflow-providers-standard; extra == 'develop'
Requires-Dist: apache-airflow<3.1,>=2.8; extra == 'develop'
Requires-Dist: build; extra == 'develop'
Requires-Dist: bump-my-version; extra == 'develop'
Requires-Dist: check-manifest; extra == 'develop'
Requires-Dist: codespell<2.5,>=2.4; extra == 'develop'
Requires-Dist: fastapi; extra == 'develop'
Requires-Dist: flask; extra == 'develop'
Requires-Dist: flask-appbuilder; extra == 'develop'
Requires-Dist: hatch-js; extra == 'develop'
Requires-Dist: hatchling; extra == 'develop'
Requires-Dist: mdformat-tables>=1; extra == 'develop'
Requires-Dist: mdformat<0.8,>=0.7.22; extra == 'develop'
Requires-Dist: pytest; extra == 'develop'
Requires-Dist: pytest-cov; extra == 'develop'
Requires-Dist: ruff; extra == 'develop'
Requires-Dist: twine; extra == 'develop'
Requires-Dist: uv; extra == 'develop'
Requires-Dist: uvicorn; extra == 'develop'
Requires-Dist: wheel; extra == 'develop'
